mra_vis/__init__.py
mra_vis-0.1.0.dist-info/METADATA
mra_vis-0.1.0.dist-info/WHEEL
mra_vis-0.1.0.dist-info/top_level.txt
mra_vis-0.1.0.dist-info/RECORD
